ckip_client-0.2.0.post1.dist-info/DESCRIPTION.rst
ckip_client-0.2.0.post1.dist-info/METADATA
ckip_client-0.2.0.post1.dist-info/RECORD
ckip_client-0.2.0.post1.dist-info/WHEEL
ckip_client-0.2.0.post1.dist-info/metadata.json
ckip_client-0.2.0.post1.dist-info/top_level.txt
ckipclient/__init__.py
ckipclient/ckip_client.py
ckipclient/ckipclient.py
ckipclient/example.py
