Metadata-Version: 2.0
Name: ckip-client
Version: 0.2.0.post1
Summary: A Python Client for CKIP Chinese Word Segmentation System
Home-page: https://github.com/yuwen41200/ckip-client
Author: Yu-wen Pwu
Author-email: ywpu@cs.nctu.edu.tw
License: MIT
Download-URL: https://pypi.python.org/pypi/ckip-client
Keywords: chinese word segmentation ckip client nlp linguistics
Platform: any
Classifier: Development Status :: 5 - Production/Stable
Classifier: Intended Audience :: Science/Research
Classifier: License :: OSI Approved :: MIT License
Classifier: Natural Language :: Chinese (Traditional)
Classifier: Programming Language :: Python :: 3
Classifier: Topic :: Text Processing :: Linguistic
Requires-Python: >=3
